{
  "html_name": "lsStmdInfoGuide",
  "label": "법령 체계도 본문 조회",
  "request_url": "http://www.law.go.kr/DRF/lawService.do?target=lsStmd요청",
  "params": [
    {
      "요청변수": "OC",
      "값": "string(필수)",
      "설명": "신청한 API인증값"
    },
    {
      "요청변수": "target",
      "값": "string : lsStmd(필수)",
      "설명": "서비스 대상"
    },
    {
      "요청변수": "type",
      "값": "char(필수)",
      "설명": "출력 형태 : HTML/XML/JSON"
    },
    {
      "요청변수": "ID",
      "값": "char",
      "설명": "법령 ID (ID 또는 MST 중 하나는 반드시 입력)"
    },
    {
      "요청변수": "MST",
      "값": "char",
      "설명": "법령 마스터 번호 - 법령테이블의 lsi_seq 값을 의미함"
    },
    {
      "요청변수": "LM",
      "값": "string",
      "설명": "법령의 법령명(법령명 입력시 해당 법령 링크)"
    },
    {
      "요청변수": "LD",
      "값": "int",
      "설명": "법령의 공포일자"
    },
    {
      "요청변수": "LN",
      "값": "int",
      "설명": "법령의 공포번호"
    }
  ],
  "response": [
    {
      "필드": "기본정보",
      "값": "string",
      "설명": "기본정보"
    },
    {
      "필드": "법령ID",
      "값": "int",
      "설명": "법령ID"
    },
    {
      "필드": "법령일련번호",
      "값": "int",
      "설명": "법령일련번호"
    },
    {
      "필드": "공포일자",
      "값": "int",
      "설명": "공포일자"
    },
    {
      "필드": "공포번호",
      "값": "int",
      "설명": "공포번호"
    },
    {
      "필드": "법종구분",
      "값": "string",
      "설명": "법종구분"
    },
    {
      "필드": "법령명",
      "값": "string",
      "설명": "법령"
    },
    {
      "필드": "시행일자",
      "값": "int",
      "설명": "시행일자"
    },
    {
      "필드": "제개정구분",
      "값": "string",
      "설명": "제개정구분"
    },
    {
      "필드": "상하위법",
      "값": "string",
      "설명": "상하위법"
    },
    {
      "필드": "법률",
      "값": "string",
      "설명": "법률"
    },
    {
      "필드": "시행령",
      "값": "string",
      "설명": "시행령"
    },
    {
      "필드": "시행규칙",
      "값": "string",
      "설명": "시행규칙"
    },
    {
      "필드": "본문 상세링크",
      "값": "string",
      "설명": "본문 상세링크"
    }
  ],
  "raw_url": "https://open.law.go.kr/LSO/openApi/guideResult.do"
}